setup.py
ircmdbot/__init__.py
ircmdbot/bot.py
ircmdbot/command_map.py
ircmdbot/config.py
ircmdbot/executor.py
ircmdbot/main.py
ircmdbot/utils.py
ircmdbot.egg-info/PKG-INFO
ircmdbot.egg-info/SOURCES.txt
ircmdbot.egg-info/dependency_links.txt
ircmdbot.egg-info/entry_points.txt
ircmdbot.egg-info/requires.txt
ircmdbot.egg-info/top_level.txt