Metadata-Version: 1.0
Name: ircmdbot
Version: 0.1
Summary: Simple IRC bot for running aliased shell commands
Home-page: https://github.com/losipiuk/ircmdbot
Author: Lukasz Osipiuk
Author-email: lukasz@osipiuk.net
License: UNKNOWN
Keywords: irc bot shell remote command
Platform: UNKNOWN
